{
  "QgtJRAgQ_Q6Ifr86AAAB": {
    "username": "🌭",
    "real": "bizzaro",
    "punti": 5,
    "prove": 3,
    "classe": "1COL",
    "livello": 5,
    "VotoPer4": 7
  },
  "a_uD0LGRjTMOzZAGAAAD": {
    "username": "🌮",
    "real": "Staiano",
    "punti": 12,
    "prove": 2,
    "classe": "1COL",
    "livello": 10,
    "VotoPer4": 22
  },
  "mCbU9HsIYjE6muNbAAAF": {
    "username": "🌯",
    "real": "Melis",
    "punti": 7,
    "prove": 1,
    "classe": "1COL",
    "livello": 7,
    "VotoPer4": 13
  },
  "Nc_A9nTlEwD4P5vSAAAH": {
    "username": "🌰",
    "real": "molon",
    "punti": 6,
    "prove": 1,
    "classe": "1COL",
    "livello": 6,
    "VotoPer4": 11
  }
}