{
  "RYVvG5kOHQ81bOelAAAC": {
    "username": "🌮",
    "real": "MariagraziaGio",
    "punti": 8,
    "prove": 0,
    "classe": "1cbr",
    "livello": 8,
    "VotoPer4": 16
  },
  "WPIEExd0T2mvnsUhAAAH": {
    "username": "🌯",
    "real": "hajar elhassou",
    "punti": 6,
    "prove": 1,
    "classe": "1cbr",
    "livello": 6,
    "VotoPer4": 11
  },
  "EIbDVFqiVz_pdXdyAAAd": {
    "username": "🌻",
    "real": "filippo cavall",
    "punti": 0,
    "prove": 0,
    "classe": "1cbr",
    "livello": 0
  }
}