{
  "4UhNk92pflXe67ysAAAC": {
    "username": "🌭",
    "real": "N Fonio",
    "punti": 18,
    "prove": 10,
    "classe": "1COL",
    "livello": 13,
    "VotoPer4": 26
  },
  "hkv4Bcgm4OgyUFTiAAAD": {
    "username": "🌮",
    "real": "E Trevisan",
    "punti": 16,
    "prove": 13,
    "classe": "1COL",
    "livello": 12,
    "VotoPer4": 19
  },
  "KFoyp21fwUjULTGuAAAF": {
    "username": "🌯",
    "real": "M Renna",
    "punti": 10,
    "prove": 5,
    "classe": "1COL",
    "livello": 9,
    "VotoPer4": 15
  },
  "fKMsD1ESEJ7UU8bqAAAH": {
    "username": "🌰",
    "real": "L Frizzi",
    "punti": 18,
    "prove": 11,
    "classe": "1COL",
    "livello": 13,
    "VotoPer4": 25
  },
  "jWxzLcZBJKBmL554AAAJ": {
    "username": "🌱",
    "real": "view",
    "punti": 0,
    "prove": 0,
    "classe": "1COL",
    "livello": 0
  }
}