{
  "uLB4hYvKElZTr8g3AAAB": {
    "username": "🌭",
    "real": "Cognome",
    "punti": 4,
    "prove": 0,
    "classe": "1MA",
    "livello": 4,
    "VotoPer4": 8
  },
  "UKgZWWrcqU45Z3z1AAAD": {
    "username": "🌮",
    "real": "Maderna",
    "punti": 6,
    "prove": 6,
    "classe": "1MA",
    "livello": 6,
    "VotoPer4": 6
  },
  "vySedFPZKqV44FAtAAAH": {
    "username": "🌯",
    "real": "Liu",
    "punti": 12,
    "prove": 0,
    "classe": "1MA",
    "livello": 10,
    "VotoPer4": 24
  },
  "STcqeLIQ4yvoswdhAAAF": {
    "username": "🌰",
    "real": "Ucci",
    "punti": 2,
    "prove": 7,
    "classe": "1MA",
    "livello": 2,
    "VotoPer4": -3
  },
  "-Crj-BrzU81m8zYzAAAJ": {
    "username": "🌱",
    "real": "Omran",
    "punti": 3,
    "prove": 5,
    "classe": "1MA",
    "livello": 3,
    "VotoPer4": 1
  },
  "W_OQcf8Xv2ATCYZpAAAN": {
    "username": "🌲",
    "real": "Masrour",
    "punti": 3,
    "prove": 1,
    "classe": "1MA",
    "livello": 3,
    "VotoPer4": 5
  },
  "bTUzuOJhVwbFxDLlAAAO": {
    "username": "🌳",
    "real": "Ierna",
    "punti": 5,
    "prove": 4,
    "classe": "1MA",
    "livello": 5,
    "VotoPer4": 6
  },
  "VhRYhU_IjrEymKQjAAAQ": {
    "username": "🌴",
    "real": "Sarr",
    "punti": 4,
    "prove": 2,
    "classe": "1MA",
    "livello": 4,
    "VotoPer4": 6
  },
  "w6B5S3nYW5I1mB7ZAAAR": {
    "username": "🌵",
    "real": "Redona",
    "punti": 2,
    "prove": 11,
    "classe": "1MA",
    "livello": 2,
    "VotoPer4": -7
  }
}